dingtalk_notify/__init__.py
dingtalk_notify/ding_talk.py
dingtalk_notify-1.0.0.dist-info/LICENSE
dingtalk_notify-1.0.0.dist-info/METADATA
dingtalk_notify-1.0.0.dist-info/WHEEL
dingtalk_notify-1.0.0.dist-info/top_level.txt
dingtalk_notify-1.0.0.dist-info/RECORD
